Metadata-Version: 1.0
Name: azhurbfunniest
Version: 0.1
Summary: The funniest joke in the world
Home-page: http://github.com/azhurb/funniest
Author: Alex Zhurbytskyi
Author-email: zhurbitsky@example.com
License: MIT
Platform: UNKNOWN
